backup2
