Metadata-Version: 1.0
Name: backup2
Version: 0.0.2.dev4
Summary: Tools for creating a backup suite
Home-page: UNKNOWN
Author: Ruben Nielsen
Author-email: nielsen.ruben@gmail.com
License: UNKNOWN
Keywords: backup,cli,commandline
Platform: UNKNOWN
